{"location":"./warehouse/yhnfl/standings","table-uuid":"010690c0-f4f2-42fa-9931-9aaecfa0aba2","last-updated-ms":1784515197588,"last-column-id":9,"schemas":[{"type":"struct","fields":[{"id":1,"name":"league_key","type":"string","required":false},{"id":2,"name":"season","type":"long","required":false},{"id":3,"name":"team_key","type":"string","required":false},{"id":4,"name":"rank","type":"long","required":false},{"id":5,"name":"wins","type":"long","required":false},{"id":6,"name":"losses","type":"long","required":false},{"id":7,"name":"ties","type":"long","required":false},{"id":8,"name":"points_for","type":"double","required":false},{"id":9,"name":"points_against","type":"double","required":false}],"schema-id":0,"identifier-field-ids":[]}],"current-schema-id":0,"partition-specs":[{"spec-id":0,"fields":[]}],"default-spec-id":0,"last-partition-id":999,"properties":{},"current-snapshot-id":6064205624649922164,"snapshots":[{"snapshot-id":6064205624649922164,"sequence-number":1,"timestamp-ms":1784515197588,"manifest-list":"./warehouse/yhnfl/standings/metadata/snap-6064205624649922164-0-e8031659-fb44-40aa-8d4d-303ddc9eccd2.avro","summary":{"operation":"append","added-files-size":"4031","added-data-files":"1","added-records":"12","total-data-files":"1","total-delete-files":"0","total-records":"12","total-files-size":"4031","total-position-deletes":"0","total-equality-deletes":"0"},"schema-id":0}],"snapshot-log":[{"snapshot-id":6064205624649922164,"timestamp-ms":1784515197588}],"metadata-log":[{"metadata-file":"./warehouse/yhnfl/standings/metadata/00000-7588499e-06a2-4a28-bd19-041ccccf6be7.metadata.json","timestamp-ms":1784515197569}],"sort-orders":[{"order-id":0,"fields":[]}],"default-sort-order-id":0,"refs":{"main":{"snapshot-id":6064205624649922164,"type":"branch"}},"statistics":[],"partition-statistics":[],"format-version":2,"last-sequence-number":1}